akimgreceiver/__init__.py
akimgreceiver/core.py
akimgreceiver-0.1.0.dist-info/METADATA
akimgreceiver-0.1.0.dist-info/WHEEL
akimgreceiver-0.1.0.dist-info/top_level.txt
akimgreceiver-0.1.0.dist-info/RECORD
