Metadata-Version: 2.4
Name: akimgreceiver
Version: 0.1.0
Summary: Simple image receiver that reads latest frame.png and deletes it.
Author: Akshay Ajit Bhawar
Requires-Python: >=3.7
Dynamic: author
Dynamic: requires-python
Dynamic: summary
